{
    "itinerary": [
        {
            "time": "17:00",
            "category": "cafe",
            "location": "스타벅스 신촌오거리점",
            "x": 37.5551906225976,
            "y": 126.934699199575
        },
        {
            "time": "18:00",
            "category": "food",
            "location": "필리앤델리 현대백화점신촌점",
            "x": 37.5558534383875,
            "y": 126.935761324635
        },
        {
            "time": "19:00",
            "category": "culture",
            "location": "소통홀",
            "x": 37.5544466505071,
            "y": 126.938525056515
        },
        {
            "time": "21:00",
            "category": "landmark",
            "location": "신촌이대거리",
            "x": 37.5573914161758,
            "y": 126.939115681116
        }
    ],
    "reasoning": [
        {
            "step": "스타벅스 신촌오거리점",
            "reason": "It's a good time to start the date with a relaxing environment to chat. The location is close to the user's starting point and other subsequent places."
        },
        {
            "step": "필리앤델리 현대백화점신촌점",
            "reason": "At 18:00, it is a perfect time for dinner. The place is conveniently located close to the cafe, ensuring a smooth transition."
        },
        {
            "step": "소통홀",
            "reason": "Starting at 19:00, this venue offers engaging cultural experiences for a good duration while fitting within the user's taste for lively environments."
        },
        {
            "step": "신촌이대거리",
            "reason": "To wrap up the night, a stroll along 신촌이대거리 is perfect. It is close by, aligns with the user's outgoing nature, and provides a lively atmosphere."
        }
    ]
}